{
  "code": "NL",
  "name": "Netherlands",
  "status": "Partial",
  "last_verified": "2026-02-15",
  "scope_notes": "Prototype compliance mapping only. Entry is partial; always validate with Dutch counsel and AFM guidance before any marketing or structuring decisions.",
  "primary_sources": [
    { "label": "AFM — Investment firms / fund registers", "url": "https://www.afm.nl/en/sector/registers" },
    { "label": "Dutch government legislation portal", "url": "https://wetten.overheid.nl/" }
  ],
  "regimes": ["AIFMD/UCITS (NL implementation)"],
  "marketing_notes": ["Marketing rules can be strict; counsel review required for any public website claims.", "Confirm investor classification and distribution channel."],
  "licensing_notes": ["Authorization/registration depends on manager/adviser/distributor role and structure."],
  "tokenization_notes": ["Tokenization requires separate securities and offering analysis."],
  "crypto_financing_notes": ["Crypto-linked features may trigger additional requirements and risk disclosures."],
  "risk_flags": ["Retail access", "Cross-border marketing", "Misclassification of activity (advice vs marketing vs management)"]
}
